{"id":"048b6fbb-0dea-4d6b-a94b-391083b27a6a","timestamp":1732567310274,"matcher":{"static":{"/api/search":{"prerender":true}},"wildcard":{},"dynamic":{}},"prerendered":["/","/guide","/guide/nuxt","/guide/faq","/guide/migration","/guide/enterprise","/components","/components/challenge-v3","/components/challenge-v2","/composables/recaptcha-provider","/composables/challenge-v2","/advanced/customize-recaptcha-script-loading","/integration/vee-validation","/composables/challenge-v3","/components/checkbox"]}